<?xml version="1.0" standalone="yes"?>
<?xml-stylesheet href="x2script.xsl" type="text/xsl"?>
<!-- Generated using X-Studio -->
<script>
	<name>plugin.jj.colour.by.race.reset.galaxy</name>
	<version>1</version>
	<engineversion>50</engineversion>
	<description>Resets coloured strings and local vars for all ships and stations across the galaxy.</description>
	<arguments />
	<sourcetext>
		<line linenr="001" indent="">
			<comment>* ************************************************</comment>
		</line>
		<line linenr="002" indent="">
			<comment>* SCRIPT NAME: Reset Galaxy</comment>
		</line>
		<line linenr="003" indent="">
			<comment>* DESCRIPTION: Resets coloured strings and local vars for all ships and stations across the galaxy.</comment>
		</line>
		<line linenr="004" indent="">
			<comment>* AUTHOR: JJ     DATE: 21 May 2023</comment>
		</line>
		<line linenr="005" indent="">
			<comment>* ************************************************</comment>
		</line>
		<line linenr="006" indent="">
			<var>$pluginData</var>
			<text> </text>
			<text>=</text>
			<text> </text>
			<text>get</text>
			<text> </text>
			<text>global</text>
			<text> </text>
			<text>variable</text>
			<text>:</text>
			<text> </text>
			<text>name</text>
			<text>=</text>
			<text>'plugin.jj.colour.by.race'</text>
		</line>
		<line linenr="007" indent="">
			<var>$pageID</var>
			<text> </text>
			<text>=</text>
			<text> </text>
			<text>array</text>
			<text> </text>
			<text>or</text>
			<text> </text>
			<text>table</text>
			<text> </text>
			<text>get</text>
			<text> </text>
			<var>$pluginData</var>
			<text> </text>
			<text>(</text>
			<var>2</var>
			<text>)</text>
		</line>
		<line linenr="008" indent="">
			<var>$debug</var>
			<text> </text>
			<text>=</text>
			<text> </text>
			<text>array</text>
			<text> </text>
			<text>or</text>
			<text> </text>
			<text>table</text>
			<text> </text>
			<text>get</text>
			<text> </text>
			<var>$pluginData</var>
			<text> </text>
			<text>(</text>
			<var>3</var>
			<text>)</text>
		</line>
		<line linenr="009" indent="">
			<text>do</text>
			<text> </text>
			<text>if</text>
			<text> </text>
			<var>$debug</var>
			<text> </text>
			<text>==</text>
			<text> </text>
			<var>[TRUE]</var>
		</line>
		<line linenr="010" indent="&#160;">
			<var>$debug</var>
			<text> </text>
			<text>=</text>
			<text> </text>
			<var>$pageID</var>
		</line>
		<line linenr="011" indent="">
			<var>$races</var>
			<text> </text>
			<text>=</text>
			<text> </text>
			<text>array</text>
			<text> </text>
			<text>or</text>
			<text> </text>
			<text>table</text>
			<text> </text>
			<text>get</text>
			<text> </text>
			<var>$pluginData</var>
			<text> </text>
			<text>(</text>
			<var>5</var>
			<text>)</text>
		</line>
		<line linenr="012" indent="">
			<var>$substringSearchArrays</var>
			<text> </text>
			<text>=</text>
			<text> </text>
			<text>array</text>
			<text> </text>
			<text>or</text>
			<text> </text>
			<text>table</text>
			<text> </text>
			<text>get</text>
			<text> </text>
			<var>$pluginData</var>
			<text> </text>
			<text>(</text>
			<var>6</var>
			<text>)</text>
		</line>
		<line linenr="013" indent="">
			<var>$ownerRaces</var>
			<text> </text>
			<text>=</text>
			<text> </text>
			<var>$races</var>
		</line>
		<line linenr="014" indent="" interruptable="@">
			<var>$stationTypes</var>
			<text> </text>
			<text>=</text>
			<text> </text>
			<var>[THIS]</var>
			<text>-&gt;</text>
			<text> </text>
			<text>call</text>
			<text> </text>
			<text>script</text>
			<text> </text>
			<call>plugin.jj.colour.by.race.getstationtypes</call>
			<text> </text>
			<text>:</text>
		</line>
		<line linenr="015" indent="" interruptable="@">
			<var>$criminalRaces</var>
			<text> </text>
			<text>=</text>
			<text> </text>
			<var>[THIS]</var>
			<text>-&gt;</text>
			<text> </text>
			<text>call</text>
			<text> </text>
			<text>script</text>
			<text> </text>
			<call>plugin.jj.colour.by.race.get.races</call>
			<text> </text>
			<text>:</text>
			<text> </text>
			<text>criminals</text>
			<text>=</text>
			<var>[TRUE]</var>
		</line>
		<line linenr="016" indent="">
			<var>$shipClasses</var>
			<text> </text>
			<text>=</text>
			<text> </text>
			<text>array</text>
			<text> </text>
			<text>alloc</text>
			<text>:</text>
			<text> </text>
			<text>size</text>
			<text>=</text>
			<var>16</var>
		</line>
		<line linenr="017" indent="">
			<text>array</text>
			<text> </text>
			<text>or</text>
			<text> </text>
			<text>table</text>
			<text> </text>
			<text>set</text>
			<text> </text>
			<var>$shipClasses</var>
			<text> </text>
			<text>(</text>
			<var>0</var>
			<text>)</text>
			<text> </text>
			<text>=</text>
			<text> </text>
			<var>[M1]</var>
		</line>
		<line linenr="018" indent="">
			<text>array</text>
			<text> </text>
			<text>or</text>
			<text> </text>
			<text>table</text>
			<text> </text>
			<text>set</text>
			<text> </text>
			<var>$shipClasses</var>
			<text> </text>
			<text>(</text>
			<var>1</var>
			<text>)</text>
			<text> </text>
			<text>=</text>
			<text> </text>
			<var>[M2]</var>
		</line>
		<line linenr="019" indent="">
			<text>array</text>
			<text> </text>
			<text>or</text>
			<text> </text>
			<text>table</text>
			<text> </text>
			<text>set</text>
			<text> </text>
			<var>$shipClasses</var>
			<text> </text>
			<text>(</text>
			<var>2</var>
			<text>)</text>
			<text> </text>
			<text>=</text>
			<text> </text>
			<var>[M3]</var>
		</line>
		<line linenr="020" indent="">
			<text>array</text>
			<text> </text>
			<text>or</text>
			<text> </text>
			<text>table</text>
			<text> </text>
			<text>set</text>
			<text> </text>
			<var>$shipClasses</var>
			<text> </text>
			<text>(</text>
			<var>3</var>
			<text>)</text>
			<text> </text>
			<text>=</text>
			<text> </text>
			<var>[M4]</var>
		</line>
		<line linenr="021" indent="">
			<text>array</text>
			<text> </text>
			<text>or</text>
			<text> </text>
			<text>table</text>
			<text> </text>
			<text>set</text>
			<text> </text>
			<var>$shipClasses</var>
			<text> </text>
			<text>(</text>
			<var>4</var>
			<text>)</text>
			<text> </text>
			<text>=</text>
			<text> </text>
			<var>[M5]</var>
		</line>
		<line linenr="022" indent="">
			<text>array</text>
			<text> </text>
			<text>or</text>
			<text> </text>
			<text>table</text>
			<text> </text>
			<text>set</text>
			<text> </text>
			<var>$shipClasses</var>
			<text> </text>
			<text>(</text>
			<var>5</var>
			<text>)</text>
			<text> </text>
			<text>=</text>
			<text> </text>
			<var>[M6]</var>
		</line>
		<line linenr="023" indent="">
			<text>array</text>
			<text> </text>
			<text>or</text>
			<text> </text>
			<text>table</text>
			<text> </text>
			<text>set</text>
			<text> </text>
			<var>$shipClasses</var>
			<text> </text>
			<text>(</text>
			<var>6</var>
			<text>)</text>
			<text> </text>
			<text>=</text>
			<text> </text>
			<var>[M7]</var>
		</line>
		<line linenr="024" indent="">
			<text>array</text>
			<text> </text>
			<text>or</text>
			<text> </text>
			<text>table</text>
			<text> </text>
			<text>set</text>
			<text> </text>
			<var>$shipClasses</var>
			<text> </text>
			<text>(</text>
			<var>7</var>
			<text>)</text>
			<text> </text>
			<text>=</text>
			<text> </text>
			<var>[M8]</var>
		</line>
		<line linenr="025" indent="">
			<text>array</text>
			<text> </text>
			<text>or</text>
			<text> </text>
			<text>table</text>
			<text> </text>
			<text>set</text>
			<text> </text>
			<var>$shipClasses</var>
			<text> </text>
			<text>(</text>
			<var>8</var>
			<text>)</text>
			<text> </text>
			<text>=</text>
			<text> </text>
			<var>[TS]</var>
		</line>
		<line linenr="026" indent="">
			<text>array</text>
			<text> </text>
			<text>or</text>
			<text> </text>
			<text>table</text>
			<text> </text>
			<text>set</text>
			<text> </text>
			<var>$shipClasses</var>
			<text> </text>
			<text>(</text>
			<var>9</var>
			<text>)</text>
			<text> </text>
			<text>=</text>
			<text> </text>
			<var>[TP]</var>
		</line>
		<line linenr="027" indent="">
			<text>array</text>
			<text> </text>
			<text>or</text>
			<text> </text>
			<text>table</text>
			<text> </text>
			<text>set</text>
			<text> </text>
			<var>$shipClasses</var>
			<text> </text>
			<text>(</text>
			<var>10</var>
			<text>)</text>
			<text> </text>
			<text>=</text>
			<text> </text>
			<var>[TM]</var>
		</line>
		<line linenr="028" indent="">
			<text>array</text>
			<text> </text>
			<text>or</text>
			<text> </text>
			<text>table</text>
			<text> </text>
			<text>set</text>
			<text> </text>
			<var>$shipClasses</var>
			<text> </text>
			<text>(</text>
			<var>11</var>
			<text>)</text>
			<text> </text>
			<text>=</text>
			<text> </text>
			<var>[TL]</var>
		</line>
		<line linenr="029" indent="">
			<text>array</text>
			<text> </text>
			<text>or</text>
			<text> </text>
			<text>table</text>
			<text> </text>
			<text>set</text>
			<text> </text>
			<var>$shipClasses</var>
			<text> </text>
			<text>(</text>
			<var>12</var>
			<text>)</text>
			<text> </text>
			<text>=</text>
			<text> </text>
			<var>[Drone]</var>
		</line>
		<line linenr="030" indent="">
			<text>array</text>
			<text> </text>
			<text>or</text>
			<text> </text>
			<text>table</text>
			<text> </text>
			<text>set</text>
			<text> </text>
			<var>$shipClasses</var>
			<text> </text>
			<text>(</text>
			<var>13</var>
			<text>)</text>
			<text> </text>
			<text>=</text>
			<text> </text>
			<var>[Lasertower]</var>
		</line>
		<line linenr="031" indent="">
			<text>array</text>
			<text> </text>
			<text>or</text>
			<text> </text>
			<text>table</text>
			<text> </text>
			<text>set</text>
			<text> </text>
			<var>$shipClasses</var>
			<text> </text>
			<text>(</text>
			<var>14</var>
			<text>)</text>
			<text> </text>
			<text>=</text>
			<text> </text>
			<var>[Goner Ship]</var>
		</line>
		<line linenr="032" indent="">
			<text>array</text>
			<text> </text>
			<text>or</text>
			<text> </text>
			<text>table</text>
			<text> </text>
			<text>set</text>
			<text> </text>
			<var>$shipClasses</var>
			<text> </text>
			<text>(</text>
			<var>15</var>
			<text>)</text>
			<text> </text>
			<text>=</text>
			<text> </text>
			<var>{Goner Ranger}</var>
		</line>
		<line linenr="033" indent="">
			<var>$prependString</var>
			<text> </text>
			<text>=</text>
			<text> </text>
			<text>'Resetting Galaxy - Coloured %s Search Array --- Race: %s --- Strings'</text>
		</line>
		<line linenr="034" indent="">
			<var>$i</var>
			<text> </text>
			<text>=</text>
			<text> </text>
			<text>size</text>
			<text> </text>
			<text>of</text>
			<text> </text>
			<text>array</text>
			<text> </text>
			<var>$races</var>
		</line>
		<line linenr="035" indent="">
			<text>while</text>
			<text> </text>
			<var>$i</var>
		</line>
		<line linenr="036" indent="&#160;">
			<text>dec</text>
			<text> </text>
			<var>$i</var>
		</line>
		<line linenr="037" indent="&#160;">
			<var>$race</var>
			<text> </text>
			<text>=</text>
			<text> </text>
			<text>array</text>
			<text> </text>
			<text>or</text>
			<text> </text>
			<text>table</text>
			<text> </text>
			<text>get</text>
			<text> </text>
			<var>$races</var>
			<text> </text>
			<text>(</text>
			<var>$i</var>
			<text>)</text>
		</line>
		<line linenr="038" indent="&#160;">
			<var>$substringSearchArray</var>
			<text> </text>
			<text>=</text>
			<text> </text>
			<text>array</text>
			<text> </text>
			<text>or</text>
			<text> </text>
			<text>table</text>
			<text> </text>
			<text>get</text>
			<text> </text>
			<var>$substringSearchArrays</var>
			<text> </text>
			<text>(</text>
			<var>$i</var>
			<text>)</text>
			<text> </text>
			<text>(</text>
			<var>1</var>
			<text>)</text>
		</line>
		<line linenr="039" indent="&#160;">
			<var>$substringSearchArrayColoured</var>
			<text> </text>
			<text>=</text>
			<text> </text>
			<text>array</text>
			<text> </text>
			<text>or</text>
			<text> </text>
			<text>table</text>
			<text> </text>
			<text>get</text>
			<text> </text>
			<var>$substringSearchArrays</var>
			<text> </text>
			<text>(</text>
			<var>$i</var>
			<text>)</text>
			<text> </text>
			<text>(</text>
			<var>3</var>
			<text>)</text>
		</line>
		<line linenr="040" indent="&#160;">
			<text>if</text>
			<text> </text>
			<var>$debug</var>
		</line>
		<line linenr="041" indent="&#160;&#160;">
			<var>$prepend</var>
			<text> </text>
			<text>=</text>
			<text> </text>
			<text>sprintf</text>
			<text>:</text>
			<text> </text>
			<text>fmt</text>
			<text>=</text>
			<var>$prependString</var>
			<text>,</text>
			<text> </text>
			<text>'Ship'</text>
			<text>,</text>
			<text> </text>
			<var>$race</var>
			<text>,</text>
			<text> </text>
			<var>null</var>
			<text>,</text>
			<text> </text>
			<var>null</var>
			<text>,</text>
			<text> </text>
			<var>null</var>
		</line>
		<line linenr="042" indent="&#160;&#160;" interruptable="@">
			<text>=</text>
			<text> </text>
			<var>[THIS]</var>
			<text>-&gt;</text>
			<text> </text>
			<text>call</text>
			<text> </text>
			<text>script</text>
			<text> </text>
			<call>plugin.jj.colour.by.race.log.array</call>
			<text> </text>
			<text>:</text>
			<text> </text>
			<text>prepend</text>
			<text>=</text>
			<var>$prepend</var>
			<text> </text>
			<text>array</text>
			<text>=</text>
			<var>$substringSearchArray</var>
			<text> </text>
			<text>logFile</text>
			<text>=</text>
			<var>$debug</var>
		</line>
		<line linenr="043" indent="&#160;">
			<text>end</text>
		</line>
		<line linenr="044" indent="&#160;">
			<var>$arrayOfObjects</var>
			<text> </text>
			<text>=</text>
			<text> </text>
			<text>array</text>
			<text> </text>
			<text>alloc</text>
			<text>:</text>
			<text> </text>
			<text>size</text>
			<text>=</text>
			<var>16</var>
		</line>
		<line linenr="045" indent="&#160;">
			<var>$j</var>
			<text> </text>
			<text>=</text>
			<text> </text>
			<text>size</text>
			<text> </text>
			<text>of</text>
			<text> </text>
			<text>array</text>
			<text> </text>
			<var>$shipClasses</var>
		</line>
		<line linenr="046" indent="&#160;">
			<text>while</text>
			<text> </text>
			<var>$j</var>
		</line>
		<line linenr="047" indent="&#160;&#160;">
			<text>dec</text>
			<text> </text>
			<var>$j</var>
		</line>
		<line linenr="048" indent="&#160;&#160;">
			<var>$class</var>
			<text> </text>
			<text>=</text>
			<text> </text>
			<text>array</text>
			<text> </text>
			<text>or</text>
			<text> </text>
			<text>table</text>
			<text> </text>
			<text>get</text>
			<text> </text>
			<var>$shipClasses</var>
			<text> </text>
			<text>(</text>
			<var>$j</var>
			<text>)</text>
		</line>
		<line linenr="049" indent="&#160;&#160;">
			<var>$objects</var>
			<text> </text>
			<text>=</text>
			<text> </text>
			<text>get</text>
			<text> </text>
			<text>ship</text>
			<text> </text>
			<text>array</text>
			<text>:</text>
			<text> </text>
			<text>of</text>
			<text> </text>
			<text>race</text>
			<text> </text>
			<var>$race</var>
			<text> </text>
			<text>class</text>
			<text>/</text>
			<text>type</text>
			<text>=</text>
			<var>$class</var>
		</line>
		<line linenr="050" indent="&#160;&#160;">
			<text>array</text>
			<text> </text>
			<text>or</text>
			<text> </text>
			<text>table</text>
			<text> </text>
			<text>set</text>
			<text> </text>
			<var>$arrayOfObjects</var>
			<text> </text>
			<text>(</text>
			<var>$j</var>
			<text>)</text>
			<text> </text>
			<text>=</text>
			<text> </text>
			<var>$objects</var>
		</line>
		<line linenr="051" indent="&#160;">
			<text>end</text>
		</line>
		<line linenr="052" indent="&#160;" interruptable="@">
			<var>$objects</var>
			<text> </text>
			<text>=</text>
			<text> </text>
			<var>[THIS]</var>
			<text>-&gt;</text>
			<text> </text>
			<text>call</text>
			<text> </text>
			<text>script</text>
			<text> </text>
			<call>plugin.jj.colour.by.race.combine.arrays</call>
			<text> </text>
			<text>:</text>
			<text> </text>
			<text>arrayOfArrays</text>
			<text>=</text>
			<var>$arrayOfObjects</var>
		</line>
		<line linenr="053" indent="&#160;">
			<text>if</text>
			<text> </text>
			<text>find</text>
			<text> </text>
			<var>$race</var>
			<text> </text>
			<text>in</text>
			<text> </text>
			<text>array</text>
			<text>:</text>
			<text> </text>
			<var>$criminalRaces</var>
		</line>
		<line linenr="054" indent="&#160;&#160;">
			<var>$XS.Iterator1</var>
			<text> </text>
			<text>=</text>
			<text> </text>
			<text>size</text>
			<text> </text>
			<text>of</text>
			<text> </text>
			<text>array</text>
			<text> </text>
			<var>$objects</var>
		</line>
		<line linenr="055" indent="&#160;&#160;">
			<text>while</text>
			<text> </text>
			<var>$XS.Iterator1</var>
		</line>
		<line linenr="056" indent="&#160;&#160;&#160;">
			<text>dec</text>
			<text> </text>
			<var>$XS.Iterator1</var>
		</line>
		<line linenr="057" indent="&#160;&#160;&#160;">
			<var>$object</var>
			<text> </text>
			<text>=</text>
			<text> </text>
			<text>array</text>
			<text> </text>
			<text>or</text>
			<text> </text>
			<text>table</text>
			<text> </text>
			<text>get</text>
			<text> </text>
			<var>$objects</var>
			<text> </text>
			<text>(</text>
			<var>$XS.Iterator1</var>
			<text>)</text>
		</line>
		<line linenr="058" indent="&#160;&#160;&#160;">
			<var>$isRenamed</var>
			<text> </text>
			<text>=</text>
			<text> </text>
			<var>$object</var>
			<text>-&gt;</text>
			<text> </text>
			<text>get</text>
			<text> </text>
			<text>local</text>
			<text> </text>
			<text>variable</text>
			<text>:</text>
			<text> </text>
			<text>name</text>
			<text>=</text>
			<text>'JJ.Set.New.Name'</text>
		</line>
		<line linenr="059" indent="&#160;&#160;&#160;">
			<text>do</text>
			<text> </text>
			<text>if</text>
			<text> </text>
			<var>$isRenamed</var>
			<text> </text>
			<text>!=</text>
			<text> </text>
			<var>[TRUE]</var>
		</line>
		<line linenr="060" indent="&#160;&#160;&#160;&#160;">
			<text>continue</text>
		</line>
		<line linenr="061" indent="&#160;&#160;&#160;">
			<var>$x</var>
			<text> </text>
			<text>=</text>
			<text> </text>
			<var>$object</var>
			<text>-&gt;</text>
			<text> </text>
			<text>get</text>
			<text> </text>
			<text>owner</text>
			<text> </text>
			<text>race</text>
		</line>
		<line linenr="062" indent="&#160;&#160;&#160;">
			<text>if</text>
			<text> </text>
			<var>$x</var>
			<text> </text>
			<text>==</text>
			<text> </text>
			<var>$race</var>
		</line>
		<line linenr="063" indent="&#160;&#160;&#160;&#160;" interruptable="@">
			<text>=</text>
			<text> </text>
			<var>$object</var>
			<text>-&gt;</text>
			<text> </text>
			<text>call</text>
			<text> </text>
			<text>script</text>
			<text> </text>
			<call>plugin.jj.colour.by.race.reset.object</call>
			<text> </text>
			<text>:</text>
			<text> </text>
			<text>substringSearchArray</text>
			<text>=</text>
			<var>$substringSearchArray</var>
			<text> </text>
			<text>substringSearchArrayColoured</text>
			<text>=</text>
			<var>$substringSearchArrayColoured</var>
			<text> </text>
			<text>debug</text>
			<text>=</text>
			<var>$debug</var>
		</line>
		<line linenr="064" indent="&#160;&#160;&#160;">
			<text>else</text>
		</line>
		<line linenr="065" indent="&#160;&#160;&#160;&#160;">
			<var>$x</var>
			<text> </text>
			<text>=</text>
			<text> </text>
			<text>get</text>
			<text> </text>
			<text>index</text>
			<text> </text>
			<text>of</text>
			<text> </text>
			<var>$x</var>
			<text> </text>
			<text>in</text>
			<text> </text>
			<text>array</text>
			<text> </text>
			<var>$races</var>
			<text> </text>
			<text>offset</text>
			<text>=</text>
			<var>-1</var>
		</line>
		<line linenr="066" indent="&#160;&#160;&#160;&#160;">
			<var>$criminalSearchArray</var>
			<text> </text>
			<text>=</text>
			<text> </text>
			<text>array</text>
			<text> </text>
			<text>or</text>
			<text> </text>
			<text>table</text>
			<text> </text>
			<text>get</text>
			<text> </text>
			<var>$substringSearchArrays</var>
			<text> </text>
			<text>(</text>
			<var>$x</var>
			<text>)</text>
			<text> </text>
			<text>(</text>
			<var>1</var>
			<text>)</text>
		</line>
		<line linenr="067" indent="&#160;&#160;&#160;&#160;">
			<var>$criminalSearchArrayColoured</var>
			<text> </text>
			<text>=</text>
			<text> </text>
			<text>array</text>
			<text> </text>
			<text>or</text>
			<text> </text>
			<text>table</text>
			<text> </text>
			<text>get</text>
			<text> </text>
			<var>$substringSearchArrays</var>
			<text> </text>
			<text>(</text>
			<var>$x</var>
			<text>)</text>
			<text> </text>
			<text>(</text>
			<var>3</var>
			<text>)</text>
		</line>
		<line linenr="068" indent="&#160;&#160;&#160;&#160;" interruptable="@">
			<text>=</text>
			<text> </text>
			<var>$object</var>
			<text>-&gt;</text>
			<text> </text>
			<text>call</text>
			<text> </text>
			<text>script</text>
			<text> </text>
			<call>plugin.jj.colour.by.race.reset.object</call>
			<text> </text>
			<text>:</text>
			<text> </text>
			<text>substringSearchArray</text>
			<text>=</text>
			<var>$criminalSearchArray</var>
			<text> </text>
			<text>substringSearchArrayColoured</text>
			<text>=</text>
			<var>$criminalSearchArrayColoured</var>
			<text> </text>
			<text>debug</text>
			<text>=</text>
			<var>$debug</var>
		</line>
		<line linenr="069" indent="&#160;&#160;&#160;">
			<text>end</text>
		</line>
		<line linenr="070" indent="&#160;&#160;">
			<text>end</text>
		</line>
		<line linenr="071" indent="&#160;">
			<text>else</text>
		</line>
		<line linenr="072" indent="&#160;&#160;">
			<text>gosub</text>
			<text> </text>
			<var>stripObjectsColours.Part</var>
			<text>:</text>
		</line>
		<line linenr="073" indent="&#160;">
			<text>end</text>
		</line>
		<line linenr="074" indent="&#160;">
			<var>$substringSearchArray</var>
			<text> </text>
			<text>=</text>
			<text> </text>
			<text>array</text>
			<text> </text>
			<text>or</text>
			<text> </text>
			<text>table</text>
			<text> </text>
			<text>get</text>
			<text> </text>
			<var>$substringSearchArrays</var>
			<text> </text>
			<text>(</text>
			<var>$i</var>
			<text>)</text>
			<text> </text>
			<text>(</text>
			<var>2</var>
			<text>)</text>
		</line>
		<line linenr="075" indent="&#160;">
			<var>$substringSearchArrayColoured</var>
			<text> </text>
			<text>=</text>
			<text> </text>
			<text>array</text>
			<text> </text>
			<text>or</text>
			<text> </text>
			<text>table</text>
			<text> </text>
			<text>get</text>
			<text> </text>
			<var>$substringSearchArrays</var>
			<text> </text>
			<text>(</text>
			<var>$i</var>
			<text>)</text>
			<text> </text>
			<text>(</text>
			<var>4</var>
			<text>)</text>
		</line>
		<line linenr="076" indent="&#160;">
			<text>if</text>
			<text> </text>
			<var>$debug</var>
			<text> </text>
			<text>==</text>
			<text> </text>
			<var>[TRUE]</var>
		</line>
		<line linenr="077" indent="&#160;&#160;">
			<var>$prepend</var>
			<text> </text>
			<text>=</text>
			<text> </text>
			<text>sprintf</text>
			<text>:</text>
			<text> </text>
			<text>fmt</text>
			<text>=</text>
			<var>$prependString</var>
			<text>,</text>
			<text> </text>
			<text>'Station'</text>
			<text>,</text>
			<text> </text>
			<var>$race</var>
			<text>,</text>
			<text> </text>
			<var>null</var>
			<text>,</text>
			<text> </text>
			<var>null</var>
			<text>,</text>
			<text> </text>
			<var>null</var>
		</line>
		<line linenr="078" indent="&#160;&#160;" interruptable="@">
			<text>=</text>
			<text> </text>
			<var>[THIS]</var>
			<text>-&gt;</text>
			<text> </text>
			<text>call</text>
			<text> </text>
			<text>script</text>
			<text> </text>
			<call>plugin.jj.colour.by.race.log.array</call>
			<text> </text>
			<text>:</text>
			<text> </text>
			<text>prepend</text>
			<text>=</text>
			<var>$prepend</var>
			<text> </text>
			<text>array</text>
			<text>=</text>
			<var>$substringSearchArrayColoured</var>
			<text> </text>
			<text>logFile</text>
			<text>=</text>
			<var>$debug</var>
		</line>
		<line linenr="079" indent="&#160;">
			<text>end</text>
		</line>
		<line linenr="080" indent="&#160;">
			<var>$types</var>
			<text> </text>
			<text>=</text>
			<text> </text>
			<text>array</text>
			<text> </text>
			<text>or</text>
			<text> </text>
			<text>table</text>
			<text> </text>
			<text>get</text>
			<text> </text>
			<var>$stationTypes</var>
			<text> </text>
			<text>(</text>
			<var>$i</var>
			<text>)</text>
		</line>
		<line linenr="081" indent="&#160;" interruptable="@">
			<var>$objects</var>
			<text> </text>
			<text>=</text>
			<text> </text>
			<var>[THIS]</var>
			<text>-&gt;</text>
			<text> </text>
			<text>call</text>
			<text> </text>
			<text>script</text>
			<text> </text>
			<call>plugin.jj.colour.by.race.get.race.stations</call>
			<text> </text>
			<text>:</text>
			<text> </text>
			<text>race</text>
			<text>=</text>
			<var>$race</var>
			<text> </text>
			<text>types</text>
			<text>=</text>
			<var>$types</var>
		</line>
		<line linenr="082" indent="&#160;" interruptable="@">
			<text>=</text>
			<text> </text>
			<var>$object</var>
			<text>-&gt;</text>
			<text> </text>
			<text>call</text>
			<text> </text>
			<text>script</text>
			<text> </text>
			<call>plugin.jj.colour.by.race.reset.object</call>
			<text> </text>
			<text>:</text>
			<text> </text>
			<text>substringSearchArray</text>
			<text>=</text>
			<var>$substringSearchArray</var>
			<text> </text>
			<text>substringSearchArrayColoured</text>
			<text>=</text>
			<var>$substringSearchArrayColoured</var>
			<text> </text>
			<text>debug</text>
			<text>=</text>
			<var>$debug</var>
		</line>
		<line linenr="083" indent="&#160;">
			<text>gosub</text>
			<text> </text>
			<var>stripObjectsColours.Part</var>
			<text>:</text>
		</line>
		<line linenr="084" indent="">
			<text>end</text>
		</line>
		<line linenr="085" indent="">
			<text>return</text>
			<text> </text>
			<var>null</var>
		</line>
		<line linenr="086" indent="" />
		<line linenr="087" indent="">
			<var>stripObjectsColours.Part</var>
			<text>:</text>
		</line>
		<line linenr="088" indent="&#160;">
			<var>$XS.Iterator2</var>
			<text> </text>
			<text>=</text>
			<text> </text>
			<text>size</text>
			<text> </text>
			<text>of</text>
			<text> </text>
			<text>array</text>
			<text> </text>
			<var>$objects</var>
		</line>
		<line linenr="089" indent="&#160;">
			<text>while</text>
			<text> </text>
			<var>$XS.Iterator2</var>
		</line>
		<line linenr="090" indent="&#160;&#160;">
			<text>dec</text>
			<text> </text>
			<var>$XS.Iterator2</var>
		</line>
		<line linenr="091" indent="&#160;&#160;">
			<var>$object</var>
			<text> </text>
			<text>=</text>
			<text> </text>
			<text>array</text>
			<text> </text>
			<text>or</text>
			<text> </text>
			<text>table</text>
			<text> </text>
			<text>get</text>
			<text> </text>
			<var>$objects</var>
			<text> </text>
			<text>(</text>
			<var>$XS.Iterator2</var>
			<text>)</text>
		</line>
		<line linenr="092" indent="&#160;&#160;">
			<var>$isRenamed</var>
			<text> </text>
			<text>=</text>
			<text> </text>
			<var>$object</var>
			<text>-&gt;</text>
			<text> </text>
			<text>get</text>
			<text> </text>
			<text>local</text>
			<text> </text>
			<text>variable</text>
			<text>:</text>
			<text> </text>
			<text>name</text>
			<text>=</text>
			<text>'JJ.Set.New.Name'</text>
		</line>
		<line linenr="093" indent="&#160;&#160;">
			<text>do</text>
			<text> </text>
			<text>if</text>
			<text> </text>
			<var>$isRenamed</var>
			<text> </text>
			<text>!=</text>
			<text> </text>
			<var>[TRUE]</var>
		</line>
		<line linenr="094" indent="&#160;&#160;&#160;">
			<text>continue</text>
		</line>
		<line linenr="095" indent="&#160;&#160;" interruptable="@">
			<text>=</text>
			<text> </text>
			<var>$object</var>
			<text>-&gt;</text>
			<text> </text>
			<text>call</text>
			<text> </text>
			<text>script</text>
			<text> </text>
			<call>plugin.jj.colour.by.race.reset.object</call>
			<text> </text>
			<text>:</text>
			<text> </text>
			<text>substringSearchArray</text>
			<text>=</text>
			<var>$substringSearchArray</var>
			<text> </text>
			<text>substringSearchArrayColoured</text>
			<text>=</text>
			<var>$substringSearchArrayColoured</var>
			<text> </text>
			<text>debug</text>
			<text>=</text>
			<var>$debug</var>
		</line>
		<line linenr="096" indent="&#160;">
			<text>end</text>
		</line>
		<line linenr="097" indent="">
			<text>endsub</text>
		</line>
	</sourcetext>
	<codearray>
		<sval type="array" size="10">
			<sval type="string" val="plugin.jj.colour.by.race.reset.galaxy" />
			<sval type="int" val="50" />
			<sval type="string" val="Resets coloured strings and local vars for all ships and stations across the galaxy." />
			<sval type="int" val="1" />
			<sval type="int" val="0" />
			<sval type="array" size="27">
				<sval type="string" val="pluginData" />
				<sval type="string" val="pageID" />
				<sval type="string" val="debug" />
				<sval type="string" val="races" />
				<sval type="string" val="substringSearchArrays" />
				<sval type="string" val="ownerRaces" />
				<sval type="string" val="stationTypes" />
				<sval type="string" val="criminalRaces" />
				<sval type="string" val="shipClasses" />
				<sval type="string" val="prependString" />
				<sval type="string" val="i" />
				<sval type="string" val="race" />
				<sval type="string" val="substringSearchArray" />
				<sval type="string" val="substringSearchArrayColoured" />
				<sval type="string" val="prepend" />
				<sval type="string" val="arrayOfObjects" />
				<sval type="string" val="j" />
				<sval type="string" val="class" />
				<sval type="string" val="objects" />
				<sval type="string" val="XS.Iterator1" />
				<sval type="string" val="object" />
				<sval type="string" val="isRenamed" />
				<sval type="string" val="x" />
				<sval type="string" val="criminalSearchArray" />
				<sval type="string" val="criminalSearchArrayColoured" />
				<sval type="string" val="types" />
				<sval type="string" val="XS.Iterator2" />
			</sval>
			<sval type="array" size="87">
				<sval type="array" size="4">
					<sval type="int" val="158" />
					<sval type="int" val="5" />
					<sval type="string" val="plugin.jj.colour.by.race" />
					<sval type="int" val="0" />
				</sval>
				<sval type="array" size="6">
					<sval type="int" val="129" />
					<sval type="int" val="1" />
					<sval type="int" val="131074" />
					<sval type="int" val="0" />
					<sval type="int" val="4" />
					<sval type="int" val="2" />
				</sval>
				<sval type="array" size="6">
					<sval type="int" val="129" />
					<sval type="int" val="2" />
					<sval type="int" val="131074" />
					<sval type="int" val="0" />
					<sval type="int" val="4" />
					<sval type="int" val="3" />
				</sval>
				<sval type="array" size="13">
					<sval type="int" val="104" />
					<sval type="int" val="-1610611448" />
					<sval type="int" val="3" />
					<sval type="int" val="131074" />
					<sval type="int" val="2" />
					<sval type="int" val="131075" />
					<sval type="int" val="10" />
					<sval type="int" val="15" />
					<sval type="int" val="0" />
					<sval type="int" val="3" />
					<sval type="int" val="-1" />
					<sval type="int" val="0" />
					<sval type="int" val="-2" />
				</sval>
				<sval type="array" size="7">
					<sval type="int" val="104" />
					<sval type="int" val="2" />
					<sval type="int" val="1" />
					<sval type="int" val="131074" />
					<sval type="int" val="1" />
					<sval type="int" val="1" />
					<sval type="int" val="-1" />
				</sval>
				<sval type="array" size="6">
					<sval type="int" val="129" />
					<sval type="int" val="3" />
					<sval type="int" val="131074" />
					<sval type="int" val="0" />
					<sval type="int" val="4" />
					<sval type="int" val="5" />
				</sval>
				<sval type="array" size="6">
					<sval type="int" val="129" />
					<sval type="int" val="4" />
					<sval type="int" val="131074" />
					<sval type="int" val="0" />
					<sval type="int" val="4" />
					<sval type="int" val="6" />
				</sval>
				<sval type="array" size="7">
					<sval type="int" val="104" />
					<sval type="int" val="5" />
					<sval type="int" val="1" />
					<sval type="int" val="131074" />
					<sval type="int" val="3" />
					<sval type="int" val="1" />
					<sval type="int" val="-1" />
				</sval>
				<sval type="array" size="6">
					<sval type="int" val="102" />
					<sval type="string" val="plugin.jj.colour.by.race.getstationtypes" />
					<sval type="int" val="6" />
					<sval type="int" val="131075" />
					<sval type="int" val="1" />
					<sval type="int" val="0" />
				</sval>
				<sval type="array" size="8">
					<sval type="int" val="102" />
					<sval type="string" val="plugin.jj.colour.by.race.get.races" />
					<sval type="int" val="7" />
					<sval type="int" val="131075" />
					<sval type="int" val="1" />
					<sval type="int" val="1" />
					<sval type="int" val="131075" />
					<sval type="int" val="10" />
				</sval>
				<sval type="array" size="4">
					<sval type="int" val="128" />
					<sval type="int" val="8" />
					<sval type="int" val="4" />
					<sval type="int" val="16" />
				</sval>
				<sval type="array" size="7">
					<sval type="int" val="130" />
					<sval type="int" val="131074" />
					<sval type="int" val="8" />
					<sval type="int" val="4" />
					<sval type="int" val="0" />
					<sval type="int" val="12" />
					<sval type="int" val="2021" />
				</sval>
				<sval type="array" size="7">
					<sval type="int" val="130" />
					<sval type="int" val="131074" />
					<sval type="int" val="8" />
					<sval type="int" val="4" />
					<sval type="int" val="1" />
					<sval type="int" val="12" />
					<sval type="int" val="2022" />
				</sval>
				<sval type="array" size="7">
					<sval type="int" val="130" />
					<sval type="int" val="131074" />
					<sval type="int" val="8" />
					<sval type="int" val="4" />
					<sval type="int" val="2" />
					<sval type="int" val="12" />
					<sval type="int" val="2023" />
				</sval>
				<sval type="array" size="7">
					<sval type="int" val="130" />
					<sval type="int" val="131074" />
					<sval type="int" val="8" />
					<sval type="int" val="4" />
					<sval type="int" val="3" />
					<sval type="int" val="12" />
					<sval type="int" val="2024" />
				</sval>
				<sval type="array" size="7">
					<sval type="int" val="130" />
					<sval type="int" val="131074" />
					<sval type="int" val="8" />
					<sval type="int" val="4" />
					<sval type="int" val="4" />
					<sval type="int" val="12" />
					<sval type="int" val="2025" />
				</sval>
				<sval type="array" size="7">
					<sval type="int" val="130" />
					<sval type="int" val="131074" />
					<sval type="int" val="8" />
					<sval type="int" val="4" />
					<sval type="int" val="5" />
					<sval type="int" val="12" />
					<sval type="int" val="2026" />
				</sval>
				<sval type="array" size="7">
					<sval type="int" val="130" />
					<sval type="int" val="131074" />
					<sval type="int" val="8" />
					<sval type="int" val="4" />
					<sval type="int" val="6" />
					<sval type="int" val="12" />
					<sval type="int" val="2027" />
				</sval>
				<sval type="array" size="7">
					<sval type="int" val="130" />
					<sval type="int" val="131074" />
					<sval type="int" val="8" />
					<sval type="int" val="4" />
					<sval type="int" val="7" />
					<sval type="int" val="12" />
					<sval type="int" val="2142" />
				</sval>
				<sval type="array" size="7">
					<sval type="int" val="130" />
					<sval type="int" val="131074" />
					<sval type="int" val="8" />
					<sval type="int" val="4" />
					<sval type="int" val="8" />
					<sval type="int" val="12" />
					<sval type="int" val="2031" />
				</sval>
				<sval type="array" size="7">
					<sval type="int" val="130" />
					<sval type="int" val="131074" />
					<sval type="int" val="8" />
					<sval type="int" val="4" />
					<sval type="int" val="9" />
					<sval type="int" val="12" />
					<sval type="int" val="2030" />
				</sval>
				<sval type="array" size="7">
					<sval type="int" val="130" />
					<sval type="int" val="131074" />
					<sval type="int" val="8" />
					<sval type="int" val="4" />
					<sval type="int" val="10" />
					<sval type="int" val="12" />
					<sval type="int" val="2141" />
				</sval>
				<sval type="array" size="7">
					<sval type="int" val="130" />
					<sval type="int" val="131074" />
					<sval type="int" val="8" />
					<sval type="int" val="4" />
					<sval type="int" val="11" />
					<sval type="int" val="12" />
					<sval type="int" val="2032" />
				</sval>
				<sval type="array" size="7">
					<sval type="int" val="130" />
					<sval type="int" val="131074" />
					<sval type="int" val="8" />
					<sval type="int" val="4" />
					<sval type="int" val="12" />
					<sval type="int" val="12" />
					<sval type="int" val="2061" />
				</sval>
				<sval type="array" size="7">
					<sval type="int" val="130" />
					<sval type="int" val="131074" />
					<sval type="int" val="8" />
					<sval type="int" val="4" />
					<sval type="int" val="13" />
					<sval type="int" val="12" />
					<sval type="int" val="2011" />
				</sval>
				<sval type="array" size="7">
					<sval type="int" val="130" />
					<sval type="int" val="131074" />
					<sval type="int" val="8" />
					<sval type="int" val="4" />
					<sval type="int" val="14" />
					<sval type="int" val="12" />
					<sval type="int" val="2039" />
				</sval>
				<sval type="array" size="7">
					<sval type="int" val="130" />
					<sval type="int" val="131074" />
					<sval type="int" val="8" />
					<sval type="int" val="4" />
					<sval type="int" val="15" />
					<sval type="int" val="9" />
					<sval type="int" val="459003" />
				</sval>
				<sval type="array" size="7">
					<sval type="int" val="104" />
					<sval type="int" val="9" />
					<sval type="int" val="1" />
					<sval type="int" val="5" />
					<sval type="string" val="Resetting Galaxy - Coloured %s Search Array --- Race: %s --- Strings" />
					<sval type="int" val="1" />
					<sval type="int" val="-1" />
				</sval>
				<sval type="array" size="4">
					<sval type="int" val="131" />
					<sval type="int" val="10" />
					<sval type="int" val="131074" />
					<sval type="int" val="3" />
				</sval>
				<sval type="array" size="7">
					<sval type="int" val="104" />
					<sval type="int" val="-1610593527" />
					<sval type="int" val="1" />
					<sval type="int" val="131074" />
					<sval type="int" val="10" />
					<sval type="int" val="1" />
					<sval type="int" val="-1" />
				</sval>
				<sval type="array" size="2">
					<sval type="int" val="143" />
					<sval type="int" val="10" />
				</sval>
				<sval type="array" size="6">
					<sval type="int" val="129" />
					<sval type="int" val="11" />
					<sval type="int" val="131074" />
					<sval type="int" val="3" />
					<sval type="int" val="131074" />
					<sval type="int" val="10" />
				</sval>
				<sval type="array" size="8">
					<sval type="int" val="1081" />
					<sval type="int" val="12" />
					<sval type="int" val="131074" />
					<sval type="int" val="4" />
					<sval type="int" val="131074" />
					<sval type="int" val="10" />
					<sval type="int" val="4" />
					<sval type="int" val="1" />
				</sval>
				<sval type="array" size="8">
					<sval type="int" val="1081" />
					<sval type="int" val="13" />
					<sval type="int" val="131074" />
					<sval type="int" val="4" />
					<sval type="int" val="131074" />
					<sval type="int" val="10" />
					<sval type="int" val="4" />
					<sval type="int" val="3" />
				</sval>
				<sval type="array" size="7">
					<sval type="int" val="104" />
					<sval type="int" val="-1610603261" />
					<sval type="int" val="1" />
					<sval type="int" val="131074" />
					<sval type="int" val="2" />
					<sval type="int" val="1" />
					<sval type="int" val="-1" />
				</sval>
				<sval type="array" size="14">
					<sval type="int" val="149" />
					<sval type="int" val="14" />
					<sval type="int" val="131074" />
					<sval type="int" val="9" />
					<sval type="int" val="5" />
					<sval type="string" val="Ship" />
					<sval type="int" val="131074" />
					<sval type="int" val="11" />
					<sval type="int" val="0" />
					<sval type="int" val="0" />
					<sval type="int" val="0" />
					<sval type="int" val="0" />
					<sval type="int" val="0" />
					<sval type="int" val="0" />
				</sval>
				<sval type="array" size="12">
					<sval type="int" val="102" />
					<sval type="string" val="plugin.jj.colour.by.race.log.array" />
					<sval type="int" val="-2147483647" />
					<sval type="int" val="131075" />
					<sval type="int" val="1" />
					<sval type="int" val="3" />
					<sval type="int" val="131074" />
					<sval type="int" val="14" />
					<sval type="int" val="131074" />
					<sval type="int" val="12" />
					<sval type="int" val="131074" />
					<sval type="int" val="2" />
				</sval>
				<sval type="array" size="4">
					<sval type="int" val="128" />
					<sval type="int" val="15" />
					<sval type="int" val="4" />
					<sval type="int" val="16" />
				</sval>
				<sval type="array" size="4">
					<sval type="int" val="131" />
					<sval type="int" val="16" />
					<sval type="int" val="131074" />
					<sval type="int" val="8" />
				</sval>
				<sval type="array" size="7">
					<sval type="int" val="104" />
					<sval type="int" val="-1610601207" />
					<sval type="int" val="1" />
					<sval type="int" val="131074" />
					<sval type="int" val="16" />
					<sval type="int" val="1" />
					<sval type="int" val="-1" />
				</sval>
				<sval type="array" size="2">
					<sval type="int" val="143" />
					<sval type="int" val="16" />
				</sval>
				<sval type="array" size="6">
					<sval type="int" val="129" />
					<sval type="int" val="17" />
					<sval type="int" val="131074" />
					<sval type="int" val="8" />
					<sval type="int" val="131074" />
					<sval type="int" val="16" />
				</sval>
				<sval type="array" size="6">
					<sval type="int" val="1068" />
					<sval type="int" val="131074" />
					<sval type="int" val="11" />
					<sval type="int" val="18" />
					<sval type="int" val="131074" />
					<sval type="int" val="17" />
				</sval>
				<sval type="array" size="7">
					<sval type="int" val="130" />
					<sval type="int" val="131074" />
					<sval type="int" val="15" />
					<sval type="int" val="131074" />
					<sval type="int" val="16" />
					<sval type="int" val="131074" />
					<sval type="int" val="18" />
				</sval>
				<sval type="array" size="2">
					<sval type="int" val="112" />
					<sval type="int" val="39" />
				</sval>
				<sval type="array" size="8">
					<sval type="int" val="102" />
					<sval type="string" val="plugin.jj.colour.by.race.combine.arrays" />
					<sval type="int" val="18" />
					<sval type="int" val="131075" />
					<sval type="int" val="1" />
					<sval type="int" val="1" />
					<sval type="int" val="131074" />
					<sval type="int" val="15" />
				</sval>
				<sval type="array" size="6">
					<sval type="int" val="1406" />
					<sval type="int" val="-1610596349" />
					<sval type="int" val="131074" />
					<sval type="int" val="11" />
					<sval type="int" val="131074" />
					<sval type="int" val="7" />
				</sval>
				<sval type="array" size="4">
					<sval type="int" val="131" />
					<sval type="int" val="19" />
					<sval type="int" val="131074" />
					<sval type="int" val="18" />
				</sval>
				<sval type="array" size="7">
					<sval type="int" val="104" />
					<sval type="int" val="-1610596599" />
					<sval type="int" val="1" />
					<sval type="int" val="131074" />
					<sval type="int" val="19" />
					<sval type="int" val="1" />
					<sval type="int" val="-1" />
				</sval>
				<sval type="array" size="2">
					<sval type="int" val="143" />
					<sval type="int" val="19" />
				</sval>
				<sval type="array" size="6">
					<sval type="int" val="129" />
					<sval type="int" val="20" />
					<sval type="int" val="131074" />
					<sval type="int" val="18" />
					<sval type="int" val="131074" />
					<sval type="int" val="19" />
				</sval>
				<sval type="array" size="6">
					<sval type="int" val="156" />
					<sval type="int" val="131074" />
					<sval type="int" val="20" />
					<sval type="int" val="5" />
					<sval type="string" val="JJ.Set.New.Name" />
					<sval type="int" val="21" />
				</sval>
				<sval type="array" size="13">
					<sval type="int" val="104" />
					<sval type="int" val="-1610598904" />
					<sval type="int" val="3" />
					<sval type="int" val="131074" />
					<sval type="int" val="21" />
					<sval type="int" val="131075" />
					<sval type="int" val="10" />
					<sval type="int" val="15" />
					<sval type="int" val="1" />
					<sval type="int" val="3" />
					<sval type="int" val="-1" />
					<sval type="int" val="1" />
					<sval type="int" val="-2" />
				</sval>
				<sval type="array" size="2">
					<sval type="int" val="112" />
					<sval type="int" val="48" />
				</sval>
				<sval type="array" size="4">
					<sval type="int" val="701" />
					<sval type="int" val="131074" />
					<sval type="int" val="20" />
					<sval type="int" val="22" />
				</sval>
				<sval type="array" size="13">
					<sval type="int" val="104" />
					<sval type="int" val="-1610597885" />
					<sval type="int" val="3" />
					<sval type="int" val="131074" />
					<sval type="int" val="22" />
					<sval type="int" val="131074" />
					<sval type="int" val="11" />
					<sval type="int" val="15" />
					<sval type="int" val="0" />
					<sval type="int" val="3" />
					<sval type="int" val="-1" />
					<sval type="int" val="0" />
					<sval type="int" val="-2" />
				</sval>
				<sval type="array" size="12">
					<sval type="int" val="102" />
					<sval type="string" val="plugin.jj.colour.by.race.reset.object" />
					<sval type="int" val="-2147483647" />
					<sval type="int" val="131074" />
					<sval type="int" val="20" />
					<sval type="int" val="3" />
					<sval type="int" val="131074" />
					<sval type="int" val="12" />
					<sval type="int" val="131074" />
					<sval type="int" val="13" />
					<sval type="int" val="131074" />
					<sval type="int" val="2" />
				</sval>
				<sval type="array" size="2">
					<sval type="int" val="112" />
					<sval type="int" val="62" />
				</sval>
				<sval type="array" size="8">
					<sval type="int" val="1083" />
					<sval type="int" val="22" />
					<sval type="int" val="131074" />
					<sval type="int" val="3" />
					<sval type="int" val="131074" />
					<sval type="int" val="22" />
					<sval type="int" val="4" />
					<sval type="int" val="-2" />
				</sval>
				<sval type="array" size="8">
					<sval type="int" val="1081" />
					<sval type="int" val="23" />
					<sval type="int" val="131074" />
					<sval type="int" val="4" />
					<sval type="int" val="131074" />
					<sval type="int" val="22" />
					<sval type="int" val="4" />
					<sval type="int" val="1" />
				</sval>
				<sval type="array" size="8">
					<sval type="int" val="1081" />
					<sval type="int" val="24" />
					<sval type="int" val="131074" />
					<sval type="int" val="4" />
					<sval type="int" val="131074" />
					<sval type="int" val="22" />
					<sval type="int" val="4" />
					<sval type="int" val="3" />
				</sval>
				<sval type="array" size="12">
					<sval type="int" val="102" />
					<sval type="string" val="plugin.jj.colour.by.race.reset.object" />
					<sval type="int" val="-2147483647" />
					<sval type="int" val="131074" />
					<sval type="int" val="20" />
					<sval type="int" val="3" />
					<sval type="int" val="131074" />
					<sval type="int" val="23" />
					<sval type="int" val="131074" />
					<sval type="int" val="24" />
					<sval type="int" val="131074" />
					<sval type="int" val="2" />
				</sval>
				<sval type="array" size="2">
					<sval type="int" val="112" />
					<sval type="int" val="48" />
				</sval>
				<sval type="array" size="2">
					<sval type="int" val="112" />
					<sval type="int" val="65" />
				</sval>
				<sval type="array" size="2">
					<sval type="int" val="1167" />
					<sval type="int" val="76" />
				</sval>
				<sval type="array" size="8">
					<sval type="int" val="1081" />
					<sval type="int" val="12" />
					<sval type="int" val="131074" />
					<sval type="int" val="4" />
					<sval type="int" val="131074" />
					<sval type="int" val="10" />
					<sval type="int" val="4" />
					<sval type="int" val="2" />
				</sval>
				<sval type="array" size="8">
					<sval type="int" val="1081" />
					<sval type="int" val="13" />
					<sval type="int" val="131074" />
					<sval type="int" val="4" />
					<sval type="int" val="131074" />
					<sval type="int" val="10" />
					<sval type="int" val="4" />
					<sval type="int" val="4" />
				</sval>
				<sval type="array" size="13">
					<sval type="int" val="104" />
					<sval type="int" val="-1610594813" />
					<sval type="int" val="3" />
					<sval type="int" val="131074" />
					<sval type="int" val="2" />
					<sval type="int" val="131075" />
					<sval type="int" val="10" />
					<sval type="int" val="15" />
					<sval type="int" val="0" />
					<sval type="int" val="3" />
					<sval type="int" val="-1" />
					<sval type="int" val="0" />
					<sval type="int" val="-2" />
				</sval>
				<sval type="array" size="14">
					<sval type="int" val="149" />
					<sval type="int" val="14" />
					<sval type="int" val="131074" />
					<sval type="int" val="9" />
					<sval type="int" val="5" />
					<sval type="string" val="Station" />
					<sval type="int" val="131074" />
					<sval type="int" val="11" />
					<sval type="int" val="0" />
					<sval type="int" val="0" />
					<sval type="int" val="0" />
					<sval type="int" val="0" />
					<sval type="int" val="0" />
					<sval type="int" val="0" />
				</sval>
				<sval type="array" size="12">
					<sval type="int" val="102" />
					<sval type="string" val="plugin.jj.colour.by.race.log.array" />
					<sval type="int" val="-2147483647" />
					<sval type="int" val="131075" />
					<sval type="int" val="1" />
					<sval type="int" val="3" />
					<sval type="int" val="131074" />
					<sval type="int" val="14" />
					<sval type="int" val="131074" />
					<sval type="int" val="13" />
					<sval type="int" val="131074" />
					<sval type="int" val="2" />
				</sval>
				<sval type="array" size="6">
					<sval type="int" val="129" />
					<sval type="int" val="25" />
					<sval type="int" val="131074" />
					<sval type="int" val="6" />
					<sval type="int" val="131074" />
					<sval type="int" val="10" />
				</sval>
				<sval type="array" size="10">
					<sval type="int" val="102" />
					<sval type="string" val="plugin.jj.colour.by.race.get.race.stations" />
					<sval type="int" val="18" />
					<sval type="int" val="131075" />
					<sval type="int" val="1" />
					<sval type="int" val="2" />
					<sval type="int" val="131074" />
					<sval type="int" val="11" />
					<sval type="int" val="131074" />
					<sval type="int" val="25" />
				</sval>
				<sval type="array" size="12">
					<sval type="int" val="102" />
					<sval type="string" val="plugin.jj.colour.by.race.reset.object" />
					<sval type="int" val="-2147483647" />
					<sval type="int" val="131074" />
					<sval type="int" val="20" />
					<sval type="int" val="3" />
					<sval type="int" val="131074" />
					<sval type="int" val="12" />
					<sval type="int" val="131074" />
					<sval type="int" val="13" />
					<sval type="int" val="131074" />
					<sval type="int" val="2" />
				</sval>
				<sval type="array" size="2">
					<sval type="int" val="1167" />
					<sval type="int" val="76" />
				</sval>
				<sval type="array" size="2">
					<sval type="int" val="112" />
					<sval type="int" val="29" />
				</sval>
				<sval type="array" size="3">
					<sval type="int" val="103" />
					<sval type="int" val="0" />
					<sval type="int" val="0" />
				</sval>
				<sval type="array" size="2">
					<sval type="int" val="101" />
					<sval type="string" val="stripObjectsColours.Part" />
				</sval>
				<sval type="array" size="4">
					<sval type="int" val="131" />
					<sval type="int" val="26" />
					<sval type="int" val="131074" />
					<sval type="int" val="18" />
				</sval>
				<sval type="array" size="7">
					<sval type="int" val="104" />
					<sval type="int" val="-1610590711" />
					<sval type="int" val="1" />
					<sval type="int" val="131074" />
					<sval type="int" val="26" />
					<sval type="int" val="1" />
					<sval type="int" val="-1" />
				</sval>
				<sval type="array" size="2">
					<sval type="int" val="143" />
					<sval type="int" val="26" />
				</sval>
				<sval type="array" size="6">
					<sval type="int" val="129" />
					<sval type="int" val="20" />
					<sval type="int" val="131074" />
					<sval type="int" val="18" />
					<sval type="int" val="131074" />
					<sval type="int" val="26" />
				</sval>
				<sval type="array" size="6">
					<sval type="int" val="156" />
					<sval type="int" val="131074" />
					<sval type="int" val="20" />
					<sval type="int" val="5" />
					<sval type="string" val="JJ.Set.New.Name" />
					<sval type="int" val="21" />
				</sval>
				<sval type="array" size="13">
					<sval type="int" val="104" />
					<sval type="int" val="-1610591224" />
					<sval type="int" val="3" />
					<sval type="int" val="131074" />
					<sval type="int" val="21" />
					<sval type="int" val="131075" />
					<sval type="int" val="10" />
					<sval type="int" val="15" />
					<sval type="int" val="1" />
					<sval type="int" val="3" />
					<sval type="int" val="-1" />
					<sval type="int" val="1" />
					<sval type="int" val="-2" />
				</sval>
				<sval type="array" size="2">
					<sval type="int" val="112" />
					<sval type="int" val="78" />
				</sval>
				<sval type="array" size="12">
					<sval type="int" val="102" />
					<sval type="string" val="plugin.jj.colour.by.race.reset.object" />
					<sval type="int" val="-2147483647" />
					<sval type="int" val="131074" />
					<sval type="int" val="20" />
					<sval type="int" val="3" />
					<sval type="int" val="131074" />
					<sval type="int" val="12" />
					<sval type="int" val="131074" />
					<sval type="int" val="13" />
					<sval type="int" val="131074" />
					<sval type="int" val="2" />
				</sval>
				<sval type="array" size="2">
					<sval type="int" val="112" />
					<sval type="int" val="78" />
				</sval>
				<sval type="array" size="1">
					<sval type="int" val="1168" />
				</sval>
			</sval>
			<sval type="int" val="0" />
			<sval type="array" size="18">
				<sval type="array" size="3">
					<sval type="int" val="0" />
					<sval type="int" val="1" />
					<sval type="string" val="************************************************" />
				</sval>
				<sval type="array" size="3">
					<sval type="int" val="0" />
					<sval type="int" val="1" />
					<sval type="string" val="SCRIPT NAME: Reset Galaxy" />
				</sval>
				<sval type="array" size="3">
					<sval type="int" val="0" />
					<sval type="int" val="1" />
					<sval type="string" val="DESCRIPTION: Resets coloured strings and local vars for all ships and stations across the galaxy." />
				</sval>
				<sval type="array" size="3">
					<sval type="int" val="0" />
					<sval type="int" val="1" />
					<sval type="string" val="AUTHOR: JJ     DATE: 21 May 2023" />
				</sval>
				<sval type="array" size="3">
					<sval type="int" val="0" />
					<sval type="int" val="1" />
					<sval type="string" val="************************************************" />
				</sval>
				<sval type="array" size="2">
					<sval type="int" val="37" />
					<sval type="int" val="4" />
				</sval>
				<sval type="array" size="2">
					<sval type="int" val="45" />
					<sval type="int" val="4" />
				</sval>
				<sval type="array" size="2">
					<sval type="int" val="54" />
					<sval type="int" val="6" />
				</sval>
				<sval type="array" size="2">
					<sval type="int" val="58" />
					<sval type="int" val="5" />
				</sval>
				<sval type="array" size="2">
					<sval type="int" val="62" />
					<sval type="int" val="4" />
				</sval>
				<sval type="array" size="2">
					<sval type="int" val="63" />
					<sval type="int" val="4" />
				</sval>
				<sval type="array" size="2">
					<sval type="int" val="64" />
					<sval type="int" val="5" />
				</sval>
				<sval type="array" size="2">
					<sval type="int" val="65" />
					<sval type="int" val="4" />
				</sval>
				<sval type="array" size="2">
					<sval type="int" val="70" />
					<sval type="int" val="4" />
				</sval>
				<sval type="array" size="2">
					<sval type="int" val="75" />
					<sval type="int" val="4" />
				</sval>
				<sval type="array" size="2">
					<sval type="int" val="76" />
					<sval type="int" val="2" />
				</sval>
				<sval type="array" size="2">
					<sval type="int" val="84" />
					<sval type="int" val="6" />
				</sval>
				<sval type="array" size="2">
					<sval type="int" val="86" />
					<sval type="int" val="4" />
				</sval>
			</sval>
			<sval type="int" val="0" />
		</sval>
	</codearray>
</script>
